lemmatizer/__init__.py
lemmatizer/const.py
lemmatizer/lemmatizer.py
lemmatizer/lookups.py
lemmatizer/data/__init__.py
lemmatizer/data/dictionary-fr-word-lemma.txt
lemmatizer-0.2.1.dist-info/LICENSE
lemmatizer-0.2.1.dist-info/METADATA
lemmatizer-0.2.1.dist-info/WHEEL
lemmatizer-0.2.1.dist-info/top_level.txt
lemmatizer-0.2.1.dist-info/RECORD
