Metadata-Version: 2.1
Name: lemmatizer
Version: 0.2.1
Summary: An lib that wrap a lemma dict as a python mapping
Home-page: https://github.com/Krozark/lemmatizer
Author: Maxime Barbier
Author-email: maxime.barbier1991+lemmatizer@gmail.com
Keywords: lemmatizer
Classifier: Programming Language :: Python
Classifier: Programming Language :: Python :: 3
Classifier: Intended Audience :: Developers
Classifier: Topic :: Software Development
Classifier: Operating System :: OS Independent
Requires-Python: >=3.6
License-File: LICENSE
